erpl/__init__.py
erpl/assets/images/moldes/molde0.jpg
erpl/assets/images/moldes/molde1.jpg
erpl/assets/images/moldes/molde10.jpg
erpl/assets/images/moldes/molde11.jpg
erpl/assets/images/moldes/molde2.jpg
erpl/assets/images/moldes/molde3.jpg
erpl/assets/images/moldes/molde4.jpg
erpl/assets/images/moldes/molde5.jpg
erpl/assets/images/moldes/molde6.jpg
erpl/assets/images/moldes/molde7.jpg
erpl/assets/images/moldes/molde8.jpg
erpl/assets/images/moldes/molde9.jpg
erpl/assets/images/seta.png
erpl/assets/objects/door/door-1-open.mp3
erpl/assets/objects/door/door-locked.mp3
erpl/assets/objects/door/door.json
erpl/assets/objects/door/door0.png
erpl/assets/objects/door/door1.png
erpl/assets/objects/door/door2.png
erpl/assets/objects/door/door3.png
erpl/assets/objects/door/door4.png
erpl/assets/objects/door/door5.png
erpl/assets/objects/safe/closed_safe.png
erpl/assets/objects/safe/open_safe.png
erpl/assets/objects/safe/safe.json
erpl/assets/objects/snowman/snowman.json
erpl/engine/game.py
erpl/engine/model/challenge.py
erpl/engine/model/escape_room.py
erpl/engine/model/event.py
erpl/engine/model/game_state.py
erpl/engine/model/hitbox.py
erpl/engine/model/inventory.py
erpl/engine/model/load.py
erpl/engine/model/object.py
erpl/engine/model/poscondition.py
erpl/engine/model/precondition.py
erpl/engine/model/precondition_tree.py
erpl/engine/model/scenario.py
erpl/engine/model/settings.py
erpl/engine/model/sound.py
erpl/engine/model/transition.py
erpl/engine/model/utils.py
erpl/engine/model/view.py
erpl/engine/pe.py
erpl/engineP5/favicon.ico
erpl/engineP5/game_model.json
erpl/engineP5/index.html
erpl/engineP5/model/challenge.js
erpl/engineP5/model/escape_room.js
erpl/engineP5/model/event.js
erpl/engineP5/model/game_state.js
erpl/engineP5/model/hitbox.js
erpl/engineP5/model/inventory.js
erpl/engineP5/model/load.js
erpl/engineP5/model/object.js
erpl/engineP5/model/p5collide.js
erpl/engineP5/model/poscondition.js
erpl/engineP5/model/precondition.js
erpl-0.1.11.dist-info/METADATA
erpl-0.1.11.dist-info/WHEEL
erpl-0.1.11.dist-info/entry_points.txt
erpl-0.1.11.dist-info/RECORD
