Metadata-Version: 2.1
Name: erpl
Version: 0.1.11
Summary: DSL for escape rooms
Author: surumkata
Author-email: a93277@uminho.pt
Requires-Python: >=3.10,<4.0
Classifier: Development Status :: 2 - Pre-Alpha
Classifier: Programming Language :: Python
Classifier: Programming Language :: Python :: 3
Classifier: Programming Language :: Python :: 3.10
Classifier: Programming Language :: Python :: 3.11
Classifier: Programming Language :: Python :: 3.12
Requires-Dist: lark (>=1.1.9,<2.0.0)
Requires-Dist: numpy (>=1.26.4,<2.0.0)
Requires-Dist: pillow (>=10.3.0,<11.0.0)
Requires-Dist: pygame (>=2.5.2,<3.0.0)
Requires-Dist: requests (>=2.32.3,<3.0.0)
